deploy/__init__.py
deploy/base.py
deploy/netlify.py
deploy/sftp.py
statik/__init__.py
statik/autogen.py
statik/cmdline.py
statik/common.py
statik/config.py
statik/context.py
statik/database.py
statik/errors.py
statik/external_database.py
statik/fields.py
statik/filters.py
statik/generator.py
statik/jinja2ext.py
statik/markdown_config.py
statik/markdown_exts.py
statik/models.py
statik/pagination.py
statik/project.py
statik/tags.py
statik/templatetags.py
statik/templating.py
statik/upload.py
statik/utils.py
statik/views.py
statik/watcher.py
statik/deploy/__init__.py
statik/deploy/base.py
statik/deploy/netlify.py
statik/deploy/sftp.py
statik/templates/index_page.html
statik/templates/model_page.html
tests/__init__.py
tests/integration/__init__.py
tests/integration/test_custom_markdown_exts.py
tests/integration/test_issue_49.py
tests/integration/test_issue_51.py
tests/integration/test_md_permalinks.py
tests/integration/test_mustache_templates.py
tests/integration/test_self_referencing_models.py
tests/integration/test_simple.py
tests/integration/test_themed.py
tests/modular/__init__.py
tests/modular/test_config.py
tests/modular/test_context.py
tests/modular/test_database.py
tests/modular/test_errors.py
tests/modular/test_external_database.py
tests/modular/test_jinja2_views.py
tests/modular/test_markdown_exts.py
tests/modular/test_models.py
tests/modular/test_nonascii.py
tests/modular/test_pagination.py
tests/modular/test_utils.py
tests/modular/test_views.py
statik-0.23.0.dist-info/LICENSE.md
statik-0.23.0.dist-info/METADATA
statik-0.23.0.dist-info/WHEEL
statik-0.23.0.dist-info/entry_points.txt
statik-0.23.0.dist-info/top_level.txt
statik-0.23.0.dist-info/RECORD
