Metadata-Version: 2.1
Name: statik
Version: 0.23.0
Summary: General-purpose static web site generator
Home-page: https://getstatik.com
Author: Thane Thomson
Author-email: connect@thanethomson.com
License: MIT
Platform: UNKNOWN
Classifier: Development Status :: 4 - Beta
Classifier: Environment :: Console
Classifier: Intended Audience :: Developers
Classifier: License :: OSI Approved :: MIT License
Classifier: Natural Language :: English
Classifier: Operating System :: POSIX
Classifier: Operating System :: MacOS
Classifier: Programming Language :: Python :: 3.6
Classifier: Programming Language :: Python :: 3.7
Classifier: Topic :: Internet :: WWW/HTTP
Classifier: Topic :: Utilities
Requires-Dist: wheel
Requires-Dist: argh (==0.26.2)
Requires-Dist: colorlog (==4.0.2)
Requires-Dist: httpwatcher (==0.5.2)
Requires-Dist: Jinja2 (==2.10.3)
Requires-Dist: lipsum (==0.1.2)
Requires-Dist: Markdown (==3.1.1)
Requires-Dist: MarkupSafe (==1.1.1)
Requires-Dist: mock (==3.0.5)
Requires-Dist: mlalchemy (==0.2.2)
Requires-Dist: pathtools (==0.1.2)
Requires-Dist: psycopg2-binary (==2.8.3)
Requires-Dist: pystache (==0.5.4)
Requires-Dist: python-dateutil (==2.8.0)
Requires-Dist: python-slugify (==3.0.4)
Requires-Dist: PyYAML (>=5.1.2)
Requires-Dist: SQLAlchemy (==1.3.9)
Requires-Dist: Unidecode (==1.1.1)
Requires-Dist: watchdog (==0.9.0)
Requires-Dist: paramiko (==2.6.0)
Requires-Dist: requests
